fplstat/__init__.py
fplstat/api/__init__.py
fplstat/api/client.py
fplstat/api/models/__init__.py
fplstat/api/models/bootstrap/bootstrap.py
fplstat/api/models/bootstrap/element.py
fplstat/api/models/fixtures.py
fplstat/fplstat.py
fplstat/transforms/__init__.py
fplstat/transforms/player.py
fplstat/utils.py
fplstat-0.3.0.dist-info/WHEEL
fplstat-0.3.0.dist-info/METADATA
fplstat-0.3.0.dist-info/RECORD
