Metadata-Version: 2.3
Name: fplstat
Version: 0.3.0
Summary: Python package for Fantasy Premier League data analysis and transformations
Author: James Leslie
Author-email: James Leslie <contactjamesleslie@gmail.com>
Requires-Dist: numpy>=2.4.1
Requires-Dist: pandas>=2.3.3
Requires-Dist: pydantic>=2.12.5
Requires-Dist: requests>=2.32.5
Requires-Dist: fastmcp>=2.14.3 ; extra == 'mcp'
Requires-Python: >=3.11
Provides-Extra: mcp
